postify/Border.py
postify/Cache.py
postify/Color.py
postify/Convert.py
postify/Crop.py
postify/Effects.py
postify/From.py
postify/Line.py
postify/Pipeline.py
postify/Procedure.py
postify/Scale.py
postify/Template.py
postify/Text.py
postify/To.py
postify/__init__.py
postify/templates/Circled.py
postify/templates/LabledTop.py
postify/templates/__init__.py
postify-0.0.4.dist-info/METADATA
postify-0.0.4.dist-info/WHEEL
postify-0.0.4.dist-info/top_level.txt
postify-0.0.4.dist-info/RECORD
