Metadata-Version: 2.1
Name: postify
Version: 0.0.4
Summary: dev@ericrobert.me
Home-page: https://github.com/eric-robert/postify
Author: Eric Robertson
Author-email: projects@ericrobert.me
License: UNKNOWN
Platform: UNKNOWN
Classifier: Programming Language :: Python :: 3
Classifier: License :: OSI Approved :: MIT License
Classifier: Operating System :: OS Independent
Requires-Python: >=3.6
